LICENSE
README.md
setup.cfg
setup.py
tls_parser/__init__.py
tls_parser/alert_protocol.py
tls_parser/application_data_protocol.py
tls_parser/change_cipher_spec_protocol.py
tls_parser/cipher_suites.py
tls_parser/exceptions.py
tls_parser/handshake_protocol.py
tls_parser/heartbeat_protocol.py
tls_parser/parser.py
tls_parser/record_protocol.py
tls_parser/tls_version.py
tls_parser.egg-info/PKG-INFO
tls_parser.egg-info/SOURCES.txt
tls_parser.egg-info/dependency_links.txt
tls_parser.egg-info/top_level.txt