Metadata-Version: 2.1
Name: tls-parser
Version: 2.0.1
Summary: Small library to parse TLS records.
Home-page: https://github.com/nabla-c0d3/tls_parser
Author: Alban Diquet
Author-email: nabla.c0d3@gmail.com
Requires-Python: >=3.7
License-File: LICENSE
